<CarSlotInfoTrans>
	<CarsOwnedByPersona/>
	<DefaultOwnedCarIndex>0</DefaultOwnedCarIndex>
	<ObtainableSlots>
		<ProductTrans>
			<BundleItems/>
			<CategoryId/>
			<Currency>CASH</Currency>
			<Description>New car slot !!</Description>
			<DurationMinute>0</DurationMinute>
			<Hash>-1143680669</Hash>
			<Icon>128_cash</Icon>
			<Level>70</Level>
			<LongDescription>New car slot !</LongDescription>
			<Price>100.0</Price>
			<Priority>0</Priority>
			<ProductId>SRV-GARAGESLOT</ProductId>
			<SecondaryIcon/>
			<UseCount>1</UseCount>
			<VisualStyle/>
			<WebIcon/>
			<WebLocation/>
		</ProductTrans>
	</ObtainableSlots>
	<OwnedCarSlotsCount>500</OwnedCarSlotsCount>
</CarSlotInfoTrans>